LICENSE.txt
README.md
setup.py
pyco_types/__init__.py
pyco_types/_cls_base.py
pyco_types/_cls_meta.py
pyco_types/_common.py
pyco_types/_convert_meta.py
pyco_types/_filter_funcs.py
pyco_types/_int_exts.py
pyco_types/_version.py
pyco_types/co_datetime.py
pyco_types/co_dict.py
pyco_types/co_ext_base.py
pyco_types/co_func.py
pyco_types/co_integer.py
pyco_types/co_interface.tmp.py
pyco_types/co_json.py
pyco_types/co_regex.py
pyco_types/const.py
pyco_types.egg-info/PKG-INFO
pyco_types.egg-info/SOURCES.txt
pyco_types.egg-info/dependency_links.txt
pyco_types.egg-info/requires.txt
pyco_types.egg-info/top_level.txt