Metadata-Version: 2.1
Name: pyco-types
Version: 1.2.6
Summary: pyco types: Flexible Extensionable Python Types with Converter
Home-page: https://github.com/vmicode/pyco-types
Author: dodoru
Author-email: dodoru@foxmail.com
License: GNU LGPLv3
Keywords: pyco-types,datetime,regex-patten,converter,type-formatter
Platform: any
Classifier: License :: OSI Approved :: MIT License
Classifier: Operating System :: OS Independent
Classifier: Programming Language :: Python
Classifier: Programming Language :: Python :: 3.7
Classifier: Programming Language :: Python :: 3.8
Classifier: Programming Language :: Python :: 3.9
Classifier: Topic :: Utilities
Classifier: Development Status :: 4 - Beta
License-File: LICENSE.txt
